{
  "play": [
    {
      "img": "img/k1.jpg",
      "title": "SCiO 微型光谱仪",
      "l_title":"可以测定食物成分及营养",
      "price": "￥ 1212",
      "zan": "3",
      "look": "3"
    },
    {
      "img": "img/k2.jpg",
      "title": "B&O BeoSound 35 音响",
      "l_title":"支持所有音乐流媒体服务",
      "price": "￥ 512",
      "zan": "3",
      "look": "3"
    },
    {
      "img": "img/k3.jpg",
      "title": "Mozbii 触控吸色笔",
      "l_title":"能吸取65000种颜色",
      "price": "￥ 暂无",
      "zan": "3",
      "look": "3"
    },
    {
      "img": "img/k4.jpg",
      "title": "XPLORER 2 航拍飞行器",
      "l_title":"搭载自动避障系统",
      "price": "￥ 433",
      "zan": "3",
      "look": "3"
    },
    {
      "img": "img/k1.jpg",
      "title": "SCiO 微型光谱仪",
      "l_title":"可以测定食物成分及营养",
      "price": "￥ 1212",
      "zan": "3",
      "look": "3"
    },
    {
      "img": "img/k2.jpg",
      "title": "B&O BeoSound 35 音响",
      "l_title":"支持所有音乐流媒体服务",
      "price": "￥ 512",
      "zan": "3",
      "look": "3"
    },
    {
      "img": "img/k3.jpg",
      "title": "Mozbii 触控吸色笔",
      "l_title":"能吸取65000种颜色",
      "price": "￥ 暂无",
      "zan": "3",
      "look": "3"
    },
    {
      "img": "img/k4.jpg",
      "title": "XPLORER 2 航拍飞行器",
      "l_title":"搭载自动避障系统",
      "price": "￥ 433",
      "zan": "3",
      "look": "3"
    },
    {
      "img": "img/k1.jpg",
      "title": "SCiO 微型光谱仪",
      "l_title":"可以测定食物成分及营养",
      "price": "￥ 1212",
      "zan": "3",
      "look": "3"
    },
    {
      "img": "img/k2.jpg",
      "title": "B&O BeoSound 35 音响",
      "l_title":"支持所有音乐流媒体服务",
      "price": "￥ 512",
      "zan": "3",
      "look": "3"
    },
    {
      "img": "img/k3.jpg",
      "title": "Mozbii 触控吸色笔",
      "l_title":"能吸取65000种颜色",
      "price": "￥ 暂无",
      "zan": "3",
      "look": "3"
    },
    {
      "img": "img/k4.jpg",
      "title": "XPLORER 2 航拍飞行器",
      "l_title":"搭载自动避障系统",
      "price": "￥ 433",
      "zan": "3",
      "look": "3"
    },
    {
      "img": "img/k1.jpg",
      "title": "SCiO 微型光谱仪",
      "l_title":"可以测定食物成分及营养",
      "price": "￥ 1212",
      "zan": "3",
      "look": "3"
    },
    {
      "img": "img/k2.jpg",
      "title": "B&O BeoSound 35 音响",
      "l_title":"支持所有音乐流媒体服务",
      "price": "￥ 512",
      "zan": "3",
      "look": "3"
    },
    {
      "img": "img/k3.jpg",
      "title": "Mozbii 触控吸色笔",
      "l_title":"能吸取65000种颜色",
      "price": "￥ 暂无",
      "zan": "3",
      "look": "3"
    },
    {
      "img": "img/k4.jpg",
      "title": "XPLORER 2 航拍飞行器",
      "l_title":"搭载自动避障系统",
      "price": "￥ 433",
      "zan": "3",
      "look": "3"
    }
  ]
}